pandabus/__init__.py
pandabus/bus.py
pandabus/event.py
pandabus-0.0.5.dist-info/LICENSE
pandabus-0.0.5.dist-info/METADATA
pandabus-0.0.5.dist-info/WHEEL
pandabus-0.0.5.dist-info/top_level.txt
pandabus-0.0.5.dist-info/RECORD
