Metadata-Version: 2.1
Name: pandabus
Version: 0.0.5
Summary: A Simple Event Bus.
Home-page: https://github.com/fired-dev/simpleeventbus
Author: Colin Xu
Author-email: colinxu2020@gmail.com
Keywords: eventbus
Classifier: Development Status :: 4 - Beta
Classifier: License :: OSI Approved :: Mozilla Public License 2.0 (MPL 2.0)
Classifier: Natural Language :: Chinese (Simplified)
Classifier: Operating System :: OS Independent
Classifier: Programming Language :: Python :: 3
Classifier: Programming Language :: Python :: 3 :: Only
Classifier: Programming Language :: Python :: 3.8
Classifier: Programming Language :: Python :: 3.9
Classifier: Programming Language :: Python :: 3.10
Classifier: Programming Language :: Python :: 3.11
Classifier: Topic :: Software Development :: Libraries
Requires-Python: >=3
License-File: LICENSE
